[
{
	"MatterSponsorId":549145,
	"MatterSponsorGuid":"5F6A4B78-BB05-4FD8-A5A0-7EE7C577BC65",
	"MatterSponsorLastModifiedUtc":"2015-08-25T15:58:09.02",
	"MatterSponsorRowVersion":"AAAAAAASZlQ=",
	"MatterSponsorMatterId":32261,
	"MatterSponsorMatterVersion":"*",
	"MatterSponsorNameId":5284,
	"MatterSponsorBodyId":null,
	"MatterSponsorName":"Albert Vann",
	"MatterSponsorSequence":7,
	"MatterSponsorLinkFlag":1
},

{
	"MatterSponsorId":549146,
	"MatterSponsorGuid":"DCCA45EB-02A7-49D1-ACBF-08F1F6EB0A1F",
	"MatterSponsorLastModifiedUtc":"2015-08-25T15:58:09.02",
	"MatterSponsorRowVersion":"AAAAAAASZlU=",
	"MatterSponsorMatterId":32261,
	"MatterSponsorMatterVersion":"*",
	"MatterSponsorNameId":5416,
	"MatterSponsorBodyId":null,
	"MatterSponsorName":"Annabel Palma",
	"MatterSponsorSequence":6,
	"MatterSponsorLinkFlag":1
},

{
	"MatterSponsorId":549147,
	"MatterSponsorGuid":"333CA88A-A975-4BA4-8088-A51F684D4C6A",
	"MatterSponsorLastModifiedUtc":"2015-08-25T15:58:09.02",
	"MatterSponsorRowVersion":"AAAAAAASZlY=",
	"MatterSponsorMatterId":32261,
	"MatterSponsorMatterVersion":"*",
	"MatterSponsorNameId":5261,
	"MatterSponsorBodyId":null,
	"MatterSponsorName":"Miguel Martinez",
	"MatterSponsorSequence":5,
	"MatterSponsorLinkFlag":1
},

{
	"MatterSponsorId":549148,
	"MatterSponsorGuid":"2C4EF5DB-F719-4418-892F-CEFAC2E5C75B",
	"MatterSponsorLastModifiedUtc":"2015-08-25T15:58:09.02",
	"MatterSponsorRowVersion":"AAAAAAASZlc=",
	"MatterSponsorMatterId":32261,
	"MatterSponsorMatterVersion":"*",
	"MatterSponsorNameId":5269,
	"MatterSponsorBodyId":null,
	"MatterSponsorName":"John C. Liu",
	"MatterSponsorSequence":4,
	"MatterSponsorLinkFlag":1
},

{
	"MatterSponsorId":549149,
	"MatterSponsorGuid":"24E322FD-631F-4EB0-AFE1-027044CD68DC",
	"MatterSponsorLastModifiedUtc":"2015-08-25T15:58:09.02",
	"MatterSponsorRowVersion":"AAAAAAASZlg=",
	"MatterSponsorMatterId":32261,
	"MatterSponsorMatterVersion":"*",
	"MatterSponsorNameId":5276,
	"MatterSponsorBodyId":null,
	"MatterSponsorName":"Leroy G. Comrie, Jr.",
	"MatterSponsorSequence":3,
	"MatterSponsorLinkFlag":1
},

{
	"MatterSponsorId":549150,
	"MatterSponsorGuid":"5833A319-7C96-4E50-A4CE-84A89B7F6579",
	"MatterSponsorLastModifiedUtc":"2015-08-25T15:58:09.02",
	"MatterSponsorRowVersion":"AAAAAAASZlk=",
	"MatterSponsorMatterId":32261,
	"MatterSponsorMatterVersion":"*",
	"MatterSponsorNameId":5287,
	"MatterSponsorBodyId":null,
	"MatterSponsorName":"Yvette D. Clarke",
	"MatterSponsorSequence":2,
	"MatterSponsorLinkFlag":1
},

{
	"MatterSponsorId":549151,
	"MatterSponsorGuid":"177FBCDE-A36B-4FA6-BDE5-AD6E68F44766",
	"MatterSponsorLastModifiedUtc":"2015-08-25T15:58:09.02",
	"MatterSponsorRowVersion":"AAAAAAASZlo=",
	"MatterSponsorMatterId":32261,
	"MatterSponsorMatterVersion":"*",
	"MatterSponsorNameId":5264,
	"MatterSponsorBodyId":null,
	"MatterSponsorName":"Maria Baez",
	"MatterSponsorSequence":1,
	"MatterSponsorLinkFlag":1
},

{
	"MatterSponsorId":549152,
	"MatterSponsorGuid":"33938A89-BBC2-403D-B0FE-43B396F7CE1C",
	"MatterSponsorLastModifiedUtc":"2015-08-25T15:58:09.02",
	"MatterSponsorRowVersion":"AAAAAAASZls=",
	"MatterSponsorMatterId":32261,
	"MatterSponsorMatterVersion":"*",
	"MatterSponsorNameId":5288,
	"MatterSponsorBodyId":null,
	"MatterSponsorName":"Charles Barron",
	"MatterSponsorSequence":0,
	"MatterSponsorLinkFlag":1
}]
