[
{
	"MatterSponsorId":912200,
	"MatterSponsorGuid":"39D64BDF-EF59-4FA1-A544-481E1DA661A2",
	"MatterSponsorLastModifiedUtc":"2015-08-25T15:58:09.02",
	"MatterSponsorRowVersion":"AAAAAADy480=",
	"MatterSponsorMatterId":47643,
	"MatterSponsorMatterVersion":"*",
	"MatterSponsorNameId":7510,
	"MatterSponsorBodyId":null,
	"MatterSponsorName":"Eric A. Ulrich",
	"MatterSponsorSequence":27,
	"MatterSponsorLinkFlag":1
},

{
	"MatterSponsorId":912201,
	"MatterSponsorGuid":"04F1F59D-9189-46B8-94D1-812DDB860B83",
	"MatterSponsorLastModifiedUtc":"2015-08-25T15:58:09.02",
	"MatterSponsorRowVersion":"AAAAAADy48w=",
	"MatterSponsorMatterId":47643,
	"MatterSponsorMatterVersion":"*",
	"MatterSponsorNameId":6267,
	"MatterSponsorBodyId":null,
	"MatterSponsorName":"Daniel R. Garodnick",
	"MatterSponsorSequence":26,
	"MatterSponsorLinkFlag":1
},

{
	"MatterSponsorId":912202,
	"MatterSponsorGuid":"04DD968F-4FB4-42BF-A269-9D596E5FB943",
	"MatterSponsorLastModifiedUtc":"2015-08-25T15:58:09.02",
	"MatterSponsorRowVersion":"AAAAAADy48s=",
	"MatterSponsorMatterId":47643,
	"MatterSponsorMatterVersion":"*",
	"MatterSponsorNameId":7569,
	"MatterSponsorBodyId":null,
	"MatterSponsorName":"James G. Van Bramer",
	"MatterSponsorSequence":25,
	"MatterSponsorLinkFlag":1
},

{
	"MatterSponsorId":912203,
	"MatterSponsorGuid":"3FB4E59C-63CD-4FD1-AA3A-FFAE70E0D078",
	"MatterSponsorLastModifiedUtc":"2015-08-25T15:58:09.02",
	"MatterSponsorRowVersion":"AAAAAADy48o=",
	"MatterSponsorMatterId":47643,
	"MatterSponsorMatterVersion":"*",
	"MatterSponsorNameId":6269,
	"MatterSponsorBodyId":null,
	"MatterSponsorName":"Melissa Mark-Viverito",
	"MatterSponsorSequence":24,
	"MatterSponsorLinkFlag":1
},

{
	"MatterSponsorId":912204,
	"MatterSponsorGuid":"9C51B7B9-6535-4A65-9EFB-7D7A55CD48B3",
	"MatterSponsorLastModifiedUtc":"2015-08-25T15:58:09.02",
	"MatterSponsorRowVersion":"AAAAAADy48k=",
	"MatterSponsorMatterId":47643,
	"MatterSponsorMatterVersion":"*",
	"MatterSponsorNameId":7567,
	"MatterSponsorBodyId":null,
	"MatterSponsorName":"Stephen T. Levin",
	"MatterSponsorSequence":23,
	"MatterSponsorLinkFlag":1
},

{
	"MatterSponsorId":912205,
	"MatterSponsorGuid":"33EC6679-EABF-4C22-9DAA-AB411FB5313B",
	"MatterSponsorLastModifiedUtc":"2015-08-25T15:58:09.02",
	"MatterSponsorRowVersion":"AAAAAADy48g=",
	"MatterSponsorMatterId":47643,
	"MatterSponsorMatterVersion":"*",
	"MatterSponsorNameId":5288,
	"MatterSponsorBodyId":null,
	"MatterSponsorName":"Charles Barron",
	"MatterSponsorSequence":22,
	"MatterSponsorLinkFlag":1
},

{
	"MatterSponsorId":912206,
	"MatterSponsorGuid":"2537F3FC-5F72-439D-B4A2-80E276AFA185",
	"MatterSponsorLastModifiedUtc":"2015-08-25T15:58:09.02",
	"MatterSponsorRowVersion":"AAAAAADy48c=",
	"MatterSponsorMatterId":47643,
	"MatterSponsorMatterVersion":"*",
	"MatterSponsorNameId":7566,
	"MatterSponsorBodyId":null,
	"MatterSponsorName":"Brad S. Lander",
	"MatterSponsorSequence":21,
	"MatterSponsorLinkFlag":1
},

{
	"MatterSponsorId":912207,
	"MatterSponsorGuid":"5FF76D40-EC25-4980-B7AD-820124BDCB0E",
	"MatterSponsorLastModifiedUtc":"2015-08-25T15:58:09.02",
	"MatterSponsorRowVersion":"AAAAAADy48Y=",
	"MatterSponsorMatterId":47643,
	"MatterSponsorMatterVersion":"*",
	"MatterSponsorNameId":7565,
	"MatterSponsorBodyId":null,
	"MatterSponsorName":"Peter A. Koo",
	"MatterSponsorSequence":20,
	"MatterSponsorLinkFlag":1
},

{
	"MatterSponsorId":912208,
	"MatterSponsorGuid":"85BEB332-1605-4BA5-86E3-F434AC0E8405",
	"MatterSponsorLastModifiedUtc":"2015-08-25T15:58:09.02",
	"MatterSponsorRowVersion":"AAAAAADy48U=",
	"MatterSponsorMatterId":47643,
	"MatterSponsorMatterVersion":"*",
	"MatterSponsorNameId":6271,
	"MatterSponsorBodyId":null,
	"MatterSponsorName":"James Vacca",
	"MatterSponsorSequence":19,
	"MatterSponsorLinkFlag":1
},

{
	"MatterSponsorId":912209,
	"MatterSponsorGuid":"F442FEDD-A9F6-47D8-A253-BCF9A7EF49C2",
	"MatterSponsorLastModifiedUtc":"2015-08-25T15:58:09.02",
	"MatterSponsorRowVersion":"AAAAAADy48Q=",
	"MatterSponsorMatterId":47643,
	"MatterSponsorMatterVersion":"*",
	"MatterSponsorNameId":7541,
	"MatterSponsorBodyId":null,
	"MatterSponsorName":"Ydanis A. Rodriguez",
	"MatterSponsorSequence":18,
	"MatterSponsorLinkFlag":1
},

{
	"MatterSponsorId":912210,
	"MatterSponsorGuid":"980578AF-2F4B-4205-9CBE-3721C5283A0A",
	"MatterSponsorLastModifiedUtc":"2015-08-25T15:58:09.02",
	"MatterSponsorRowVersion":"AAAAAADy48M=",
	"MatterSponsorMatterId":47643,
	"MatterSponsorMatterVersion":"*",
	"MatterSponsorNameId":7571,
	"MatterSponsorBodyId":null,
	"MatterSponsorName":"Jumaane D. Williams",
	"MatterSponsorSequence":17,
	"MatterSponsorLinkFlag":1
},

{
	"MatterSponsorId":912211,
	"MatterSponsorGuid":"6359DBB7-0ACA-4941-B98E-75D2643480D8",
	"MatterSponsorLastModifiedUtc":"2015-08-25T15:58:09.02",
	"MatterSponsorRowVersion":"AAAAAADy48I=",
	"MatterSponsorMatterId":47643,
	"MatterSponsorMatterVersion":"*",
	"MatterSponsorNameId":5284,
	"MatterSponsorBodyId":null,
	"MatterSponsorName":"Albert Vann",
	"MatterSponsorSequence":16,
	"MatterSponsorLinkFlag":1
},

{
	"MatterSponsorId":912212,
	"MatterSponsorGuid":"3631CB26-2B69-4E2A-83E6-C6EE70128895",
	"MatterSponsorLastModifiedUtc":"2015-08-25T15:58:09.02",
	"MatterSponsorRowVersion":"AAAAAADy48E=",
	"MatterSponsorMatterId":47643,
	"MatterSponsorMatterVersion":"*",
	"MatterSponsorNameId":7568,
	"MatterSponsorBodyId":null,
	"MatterSponsorName":"Deborah L. Rose",
	"MatterSponsorSequence":15,
	"MatterSponsorLinkFlag":1
},

{
	"MatterSponsorId":912213,
	"MatterSponsorGuid":"488709C8-A1FC-486C-A551-A90EFA42EC4C",
	"MatterSponsorLastModifiedUtc":"2015-08-25T15:58:09.02",
	"MatterSponsorRowVersion":"AAAAAADy48A=",
	"MatterSponsorMatterId":47643,
	"MatterSponsorMatterVersion":"*",
	"MatterSponsorNameId":5256,
	"MatterSponsorBodyId":null,
	"MatterSponsorName":"Diana Reyna",
	"MatterSponsorSequence":14,
	"MatterSponsorLinkFlag":1
},

{
	"MatterSponsorId":912214,
	"MatterSponsorGuid":"E3B378EA-351E-47BB-A3AF-CBE11BD0183D",
	"MatterSponsorLastModifiedUtc":"2015-08-25T15:58:09.02",
	"MatterSponsorRowVersion":"AAAAAADy478=",
	"MatterSponsorMatterId":47643,
	"MatterSponsorMatterVersion":"*",
	"MatterSponsorNameId":435,
	"MatterSponsorBodyId":null,
	"MatterSponsorName":"Michael C. Nelson",
	"MatterSponsorSequence":13,
	"MatterSponsorLinkFlag":1
},

{
	"MatterSponsorId":912215,
	"MatterSponsorGuid":"D42E7190-6A40-469D-82FD-43F77D7777CB",
	"MatterSponsorLastModifiedUtc":"2015-08-25T15:58:09.02",
	"MatterSponsorRowVersion":"AAAAAADy474=",
	"MatterSponsorMatterId":47643,
	"MatterSponsorMatterVersion":"*",
	"MatterSponsorNameId":6274,
	"MatterSponsorBodyId":null,
	"MatterSponsorName":"Rosie Mendez",
	"MatterSponsorSequence":12,
	"MatterSponsorLinkFlag":1
},

{
	"MatterSponsorId":912216,
	"MatterSponsorGuid":"38B253E5-4B1F-4793-B5D9-D0B21A037139",
	"MatterSponsorLastModifiedUtc":"2015-08-25T15:58:09.02",
	"MatterSponsorRowVersion":"AAAAAADy470=",
	"MatterSponsorMatterId":47643,
	"MatterSponsorMatterVersion":"*",
	"MatterSponsorNameId":386,
	"MatterSponsorBodyId":null,
	"MatterSponsorName":"Karen Koslowitz",
	"MatterSponsorSequence":11,
	"MatterSponsorLinkFlag":1
},

{
	"MatterSponsorId":912217,
	"MatterSponsorGuid":"21020017-C69B-4703-9D11-F9682D8417AE",
	"MatterSponsorLastModifiedUtc":"2015-08-25T15:58:09.02",
	"MatterSponsorRowVersion":"AAAAAADy47w=",
	"MatterSponsorMatterId":47643,
	"MatterSponsorMatterVersion":"*",
	"MatterSponsorNameId":5262,
	"MatterSponsorBodyId":null,
	"MatterSponsorName":"G. Oliver Koppell",
	"MatterSponsorSequence":10,
	"MatterSponsorLinkFlag":1
},

{
	"MatterSponsorId":912218,
	"MatterSponsorGuid":"658BC15B-4319-480F-BB51-E53867E968EC",
	"MatterSponsorLastModifiedUtc":"2015-08-25T15:58:09.02",
	"MatterSponsorRowVersion":"AAAAAADy47s=",
	"MatterSponsorMatterId":47643,
	"MatterSponsorMatterVersion":"*",
	"MatterSponsorNameId":5417,
	"MatterSponsorBodyId":null,
	"MatterSponsorName":"Letitia James",
	"MatterSponsorSequence":9,
	"MatterSponsorLinkFlag":1
},

{
	"MatterSponsorId":912219,
	"MatterSponsorGuid":"01DD44BF-6CEC-4F83-A0F3-6A774E9D5458",
	"MatterSponsorLastModifiedUtc":"2015-08-25T15:58:09.02",
	"MatterSponsorRowVersion":"AAAAAADy47o=",
	"MatterSponsorMatterId":47643,
	"MatterSponsorMatterVersion":"*",
	"MatterSponsorNameId":5260,
	"MatterSponsorBodyId":null,
	"MatterSponsorName":"Robert Jackson",
	"MatterSponsorSequence":8,
	"MatterSponsorLinkFlag":1
},

{
	"MatterSponsorId":912220,
	"MatterSponsorGuid":"AA734CF2-F4FE-4331-835B-ADA5928977DC",
	"MatterSponsorLastModifiedUtc":"2015-08-25T15:58:09.02",
	"MatterSponsorRowVersion":"AAAAAADy47k=",
	"MatterSponsorMatterId":47643,
	"MatterSponsorMatterVersion":"*",
	"MatterSponsorNameId":5376,
	"MatterSponsorBodyId":null,
	"MatterSponsorName":"Sara M. Gonzalez",
	"MatterSponsorSequence":7,
	"MatterSponsorLinkFlag":1
},

{
	"MatterSponsorId":912221,
	"MatterSponsorGuid":"0FF1C76D-16BC-45C8-8D0D-4B1A188DA373",
	"MatterSponsorLastModifiedUtc":"2015-08-25T15:58:09.02",
	"MatterSponsorRowVersion":"AAAAAADy47g=",
	"MatterSponsorMatterId":47643,
	"MatterSponsorMatterVersion":"*",
	"MatterSponsorNameId":5390,
	"MatterSponsorBodyId":null,
	"MatterSponsorName":"Vincent J. Gentile",
	"MatterSponsorSequence":6,
	"MatterSponsorLinkFlag":1
},

{
	"MatterSponsorId":912222,
	"MatterSponsorGuid":"F146E953-A9AC-4BC7-838F-04670A5EB763",
	"MatterSponsorLastModifiedUtc":"2015-08-25T15:58:09.02",
	"MatterSponsorRowVersion":"AAAAAADy47c=",
	"MatterSponsorMatterId":47643,
	"MatterSponsorMatterVersion":"*",
	"MatterSponsorNameId":7509,
	"MatterSponsorBodyId":null,
	"MatterSponsorName":"Julissa Ferreras-Copeland",
	"MatterSponsorSequence":5,
	"MatterSponsorLinkFlag":1
},

{
	"MatterSponsorId":912223,
	"MatterSponsorGuid":"69B0DF78-7309-40E2-A754-7CF27E957472",
	"MatterSponsorLastModifiedUtc":"2015-08-25T15:58:09.02",
	"MatterSponsorRowVersion":"AAAAAADy47Y=",
	"MatterSponsorMatterId":47643,
	"MatterSponsorMatterVersion":"*",
	"MatterSponsorNameId":7113,
	"MatterSponsorBodyId":null,
	"MatterSponsorName":"Mathieu Eugene",
	"MatterSponsorSequence":4,
	"MatterSponsorLinkFlag":1
},

{
	"MatterSponsorId":912224,
	"MatterSponsorGuid":"97F87D6E-F683-483F-995D-612CEB9482E8",
	"MatterSponsorLastModifiedUtc":"2015-08-25T15:58:09.02",
	"MatterSponsorRowVersion":"AAAAAADy47U=",
	"MatterSponsorMatterId":47643,
	"MatterSponsorMatterVersion":"*",
	"MatterSponsorNameId":7562,
	"MatterSponsorBodyId":null,
	"MatterSponsorName":"Margaret S. Chin",
	"MatterSponsorSequence":3,
	"MatterSponsorLinkFlag":1
},

{
	"MatterSponsorId":912225,
	"MatterSponsorGuid":"085C9354-B817-4AFD-A4CF-B06A7866C8E2",
	"MatterSponsorLastModifiedUtc":"2015-08-25T15:58:09.02",
	"MatterSponsorRowVersion":"AAAAAADy47Q=",
	"MatterSponsorMatterId":47643,
	"MatterSponsorMatterVersion":"*",
	"MatterSponsorNameId":5259,
	"MatterSponsorBodyId":null,
	"MatterSponsorName":"Gale A. Brewer",
	"MatterSponsorSequence":2,
	"MatterSponsorLinkFlag":1
},

{
	"MatterSponsorId":912226,
	"MatterSponsorGuid":"87AFEB8E-7041-4862-9012-8D2FB72968DA",
	"MatterSponsorLastModifiedUtc":"2015-08-25T15:58:09.02",
	"MatterSponsorRowVersion":"AAAAAADy47M=",
	"MatterSponsorMatterId":47643,
	"MatterSponsorMatterVersion":"*",
	"MatterSponsorNameId":5911,
	"MatterSponsorBodyId":null,
	"MatterSponsorName":"Maria Del Carmen Arroyo",
	"MatterSponsorSequence":1,
	"MatterSponsorLinkFlag":1
},

{
	"MatterSponsorId":912227,
	"MatterSponsorGuid":"79788FC3-C434-4A6E-9D60-7308F73F2E9E",
	"MatterSponsorLastModifiedUtc":"2015-08-25T15:58:09.02",
	"MatterSponsorRowVersion":"AAAAAADy47I=",
	"MatterSponsorMatterId":47643,
	"MatterSponsorMatterVersion":"*",
	"MatterSponsorNameId":7563,
	"MatterSponsorBodyId":null,
	"MatterSponsorName":"Daniel Dromm ",
	"MatterSponsorSequence":0,
	"MatterSponsorLinkFlag":1
}]
