[
{
	"MatterSponsorId":403184,
	"MatterSponsorGuid":"7F23279E-032D-4843-8D2D-468D930554CB",
	"MatterSponsorLastModifiedUtc":"2015-08-25T15:58:09.02",
	"MatterSponsorRowVersion":"AAAAAAARxUI=",
	"MatterSponsorMatterId":24179,
	"MatterSponsorMatterVersion":"*",
	"MatterSponsorNameId":15,
	"MatterSponsorBodyId":null,
	"MatterSponsorName":"Wendell Foster",
	"MatterSponsorSequence":0,
	"MatterSponsorLinkFlag":1
},

{
	"MatterSponsorId":403185,
	"MatterSponsorGuid":"474A95A0-AC3A-4996-AE8E-68D99958EFCE",
	"MatterSponsorLastModifiedUtc":"2015-08-25T15:58:09.02",
	"MatterSponsorRowVersion":"AAAAAAARxUM=",
	"MatterSponsorMatterId":24179,
	"MatterSponsorMatterVersion":"*",
	"MatterSponsorNameId":12,
	"MatterSponsorBodyId":null,
	"MatterSponsorName":"Stanley E. Michels",
	"MatterSponsorSequence":1,
	"MatterSponsorLinkFlag":1
},

{
	"MatterSponsorId":403186,
	"MatterSponsorGuid":"08D3AF27-DF64-4E34-BDB7-F9E0234F7558",
	"MatterSponsorLastModifiedUtc":"2015-08-25T15:58:09.02",
	"MatterSponsorRowVersion":"AAAAAAARxUQ=",
	"MatterSponsorMatterId":24179,
	"MatterSponsorMatterVersion":"*",
	"MatterSponsorNameId":424,
	"MatterSponsorBodyId":null,
	"MatterSponsorName":"Tracy L. Boyland",
	"MatterSponsorSequence":2,
	"MatterSponsorLinkFlag":1
},

{
	"MatterSponsorId":403187,
	"MatterSponsorGuid":"909271D1-280D-4892-978C-592DA53607DD",
	"MatterSponsorLastModifiedUtc":"2015-08-25T15:58:09.02",
	"MatterSponsorRowVersion":"AAAAAAARxUU=",
	"MatterSponsorMatterId":24179,
	"MatterSponsorMatterVersion":"*",
	"MatterSponsorNameId":5227,
	"MatterSponsorBodyId":null,
	"MatterSponsorName":"Michael J. Abel",
	"MatterSponsorSequence":3,
	"MatterSponsorLinkFlag":1
},

{
	"MatterSponsorId":403188,
	"MatterSponsorGuid":"95933FC0-D709-4006-BBFA-03AE55610E45",
	"MatterSponsorLastModifiedUtc":"2015-08-25T15:58:09.02",
	"MatterSponsorRowVersion":"AAAAAAARxUY=",
	"MatterSponsorMatterId":24179,
	"MatterSponsorMatterVersion":"*",
	"MatterSponsorNameId":420,
	"MatterSponsorBodyId":null,
	"MatterSponsorName":"Alphonse Stabile",
	"MatterSponsorSequence":4,
	"MatterSponsorLinkFlag":1
},

{
	"MatterSponsorId":403189,
	"MatterSponsorGuid":"84CC56F0-B5D8-4377-BA6F-72BAB9BEA3E5",
	"MatterSponsorLastModifiedUtc":"2015-08-25T15:58:09.02",
	"MatterSponsorRowVersion":"AAAAAAARxUc=",
	"MatterSponsorMatterId":24179,
	"MatterSponsorMatterVersion":"*",
	"MatterSponsorNameId":null,
	"MatterSponsorBodyId":43,
	"MatterSponsorName":"(by request of the Mayor)",
	"MatterSponsorSequence":5,
	"MatterSponsorLinkFlag":1
},

{
	"MatterSponsorId":403190,
	"MatterSponsorGuid":"B3425B05-8271-4593-96AC-6BDF60ABEF28",
	"MatterSponsorLastModifiedUtc":"2015-08-25T15:58:09.02",
	"MatterSponsorRowVersion":"AAAAAAARxUg=",
	"MatterSponsorMatterId":24179,
	"MatterSponsorMatterVersion":"*",
	"MatterSponsorNameId":7,
	"MatterSponsorBodyId":null,
	"MatterSponsorName":"Jerome X. O'Donovan",
	"MatterSponsorSequence":6,
	"MatterSponsorLinkFlag":1
},

{
	"MatterSponsorId":403191,
	"MatterSponsorGuid":"9358DD23-9EF0-4291-A6D8-753783CF0867",
	"MatterSponsorLastModifiedUtc":"2015-08-25T15:58:09.02",
	"MatterSponsorRowVersion":"AAAAAAARxUk=",
	"MatterSponsorMatterId":24179,
	"MatterSponsorMatterVersion":"*",
	"MatterSponsorNameId":24,
	"MatterSponsorBodyId":null,
	"MatterSponsorName":"Morton Povman",
	"MatterSponsorSequence":7,
	"MatterSponsorLinkFlag":1
}]
