{
    "EventItemId": 213990,
    "EventItemGuid": "A2ECECF1-7924-4901-9448-BE1CCFB48CC4",
    "EventItemLastModifiedUtc": "2015-08-25T15:58:59.527",
    "EventItemRowVersion": "AAAAAAAGuzI=",
    "EventItemEventId": 8154,
    "EventItemAgendaSequence": 1,
    "EventItemMinutesSequence": 3,
    "EventItemAgendaNumber": null,
    "EventItemVideo": null,
    "EventItemVideoIndex": null,
    "EventItemVersion": "*",
    "EventItemAgendaNote": null,
    "EventItemMinutesNote": null,
    "EventItemActionId": 54,
    "EventItemActionName": "Hearing Held by Committee",
    "EventItemActionText": "This Oversight was Hearing Held by Committee",
    "EventItemPassedFlag": null,
    "EventItemPassedFlagName": null,
    "EventItemRollCallFlag": 0,
    "EventItemFlagExtra": 0,
    "EventItemTitle": "Oversight - ACS' efforts to preserve child care centers in NYC",
    "EventItemTally": null,
    "EventItemAccelaRecordId": null,
    "EventItemConsent": 0,
    "EventItemMoverId": null,
    "EventItemMover": null,
    "EventItemSeconderId": null,
    "EventItemSeconder": null,
    "EventItemMatterId": 40714,
    "EventItemMatterGuid": "4C5074F0-6522-4F02-8DDF-FF923B0BF0E7",
    "EventItemMatterFile": "T2008-0507",
    "EventItemMatterName": "Oversight - ACS' efforts to preserve child care centers in NYC",
    "EventItemMatterType": "Oversight",
    "EventItemMatterStatus": "Filed",
    "EventItemMatterAttachments": []
},{
    "EventItemId": 214178,
    "EventItemGuid": "729D5560-4137-4D6E-8ECA-5D8A034005F3",
    "EventItemLastModifiedUtc": "2015-08-25T15:58:59.527",
    "EventItemRowVersion": "AAAAAAAGvQQ=",
    "EventItemEventId": 8154,
    "EventItemAgendaSequence": null,
    "EventItemMinutesSequence": 4,
    "EventItemAgendaNumber": null,
    "EventItemVideo": null,
    "EventItemVideoIndex": null,
    "EventItemVersion": "*",
    "EventItemAgendaNote": null,
    "EventItemMinutesNote": null,
    "EventItemActionId": 5031,
    "EventItemActionName": "Filed, by Committee",
    "EventItemActionText": "This Oversight was Filed, by Committee",
    "EventItemPassedFlag": null,
    "EventItemPassedFlagName": null,
    "EventItemRollCallFlag": 0,
    "EventItemFlagExtra": 0,
    "EventItemTitle": "Oversight - ACS' efforts to preserve child care centers in NYC",
    "EventItemTally": null,
    "EventItemAccelaRecordId": null,
    "EventItemConsent": 0,
    "EventItemMoverId": null,
    "EventItemMover": null,
    "EventItemSeconderId": null,
    "EventItemSeconder": null,
    "EventItemMatterId": 40714,
    "EventItemMatterGuid": "4C5074F0-6522-4F02-8DDF-FF923B0BF0E7",
    "EventItemMatterFile": "T2008-0507",
    "EventItemMatterName": "Oversight - ACS' efforts to preserve child care centers in NYC",
    "EventItemMatterType": "Oversight",
    "EventItemMatterStatus": "Filed",
    "EventItemMatterAttachments": []
},{
    "EventItemId": 214179,
    "EventItemGuid": "748BDDAF-5E91-423C-9E9A-143B729FC343",
    "EventItemLastModifiedUtc": "2015-08-25T15:58:59.527",
    "EventItemRowVersion": "AAAAAAAGvQY=",
    "EventItemEventId": 8154,
    "EventItemAgendaSequence": null,
    "EventItemMinutesSequence": 1,
    "EventItemAgendaNumber": null,
    "EventItemVideo": null,
    "EventItemVideoIndex": null,
    "EventItemVersion": null,
    "EventItemAgendaNote": null,
    "EventItemMinutesNote": null,
    "EventItemActionId": null,
    "EventItemActionName": null,
    "EventItemActionText": null,
    "EventItemPassedFlag": null,
    "EventItemPassedFlagName": null,
    "EventItemRollCallFlag": 1,
    "EventItemFlagExtra": 0,
    "EventItemTitle": "Roll Call",
    "EventItemTally": null,
    "EventItemAccelaRecordId": null,
    "EventItemConsent": 0,
    "EventItemMoverId": null,
    "EventItemMover": null,
    "EventItemSeconderId": null,
    "EventItemSeconder": null,
    "EventItemMatterId": null,
    "EventItemMatterGuid": null,
    "EventItemMatterFile": null,
    "EventItemMatterName": null,
    "EventItemMatterType": null,
    "EventItemMatterStatus": null,
    "EventItemMatterAttachments": []
},{
    "EventItemId": 214439,
    "EventItemGuid": "45F21C69-DD2B-42A2-9939-9DF88BE47D9D",
    "EventItemLastModifiedUtc": "2015-08-25T15:58:59.527",
    "EventItemRowVersion": "AAAAAAAGv0g=",
    "EventItemEventId": 8154,
    "EventItemAgendaSequence": null,
    "EventItemMinutesSequence": 2,
    "EventItemAgendaNumber": null,
    "EventItemVideo": null,
    "EventItemVideoIndex": null,
    "EventItemVersion": null,
    "EventItemAgendaNote": null,
    "EventItemMinutesNote": null,
    "EventItemActionId": null,
    "EventItemActionName": null,
    "EventItemActionText": null,
    "EventItemPassedFlag": null,
    "EventItemPassedFlagName": null,
    "EventItemRollCallFlag": 0,
    "EventItemFlagExtra": 0,
    "EventItemTitle": null,
    "EventItemTally": null,
    "EventItemAccelaRecordId": null,
    "EventItemConsent": 0,
    "EventItemMoverId": null,
    "EventItemMover": null,
    "EventItemSeconderId": null,
    "EventItemSeconder": null,
    "EventItemMatterId": null,
    "EventItemMatterGuid": null,
    "EventItemMatterFile": null,
    "EventItemMatterName": null,
    "EventItemMatterType": null,
    "EventItemMatterStatus": null,
    "EventItemMatterAttachments": []
},