{
    "EventItemId": 287236,
    "EventItemGuid": "CE6D8235-0BB2-46B2-A8BE-04F2F1B1BC5F",
    "EventItemLastModifiedUtc": "2015-08-25T15:58:59.527",
    "EventItemRowVersion": "AAAAAB9qkRc=",
    "EventItemEventId": 13196,
    "EventItemAgendaSequence": 1,
    "EventItemMinutesSequence": 3,
    "EventItemAgendaNumber": null,
    "EventItemVideo": null,
    "EventItemVideoIndex": null,
    "EventItemVersion": "*",
    "EventItemAgendaNote": null,
    "EventItemMinutesNote": null,
    "EventItemActionId": 54,
    "EventItemActionName": "Hearing Held by Committee",
    "EventItemActionText": "This Oversight was Hearing Held by Committee",
    "EventItemPassedFlag": null,
    "EventItemPassedFlagName": null,
    "EventItemRollCallFlag": 0,
    "EventItemFlagExtra": null,
    "EventItemTitle": "Oversight – Is the City doing enough to increase access to capital and credit readiness for small businesses?",
    "EventItemTally": null,
    "EventItemAccelaRecordId": null,
    "EventItemConsent": 0,
    "EventItemMoverId": null,
    "EventItemMover": null,
    "EventItemSeconderId": null,
    "EventItemSeconder": null,
    "EventItemMatterId": 52441,
    "EventItemMatterGuid": "AD00C423-2879-45A4-A8CD-07741F4139E5",
    "EventItemMatterFile": "T2014-0907",
    "EventItemMatterName": "Oversight – Is the City doing enough to increase access to capital and credit readiness for small businesses?",
    "EventItemMatterType": "Oversight",
    "EventItemMatterStatus": "Filed",
    "EventItemMatterAttachments": []
},{
    "EventItemId": 287664,
    "EventItemGuid": "B262E663-EB6C-4BFB-9D65-AFC88C46C804",
    "EventItemLastModifiedUtc": "2015-08-25T15:58:59.527",
    "EventItemRowVersion": "AAAAAB9qkUQ=",
    "EventItemEventId": 13196,
    "EventItemAgendaSequence": null,
    "EventItemMinutesSequence": 1,
    "EventItemAgendaNumber": null,
    "EventItemVideo": null,
    "EventItemVideoIndex": null,
    "EventItemVersion": null,
    "EventItemAgendaNote": null,
    "EventItemMinutesNote": null,
    "EventItemActionId": null,
    "EventItemActionName": null,
    "EventItemActionText": null,
    "EventItemPassedFlag": null,
    "EventItemPassedFlagName": null,
    "EventItemRollCallFlag": 1,
    "EventItemFlagExtra": null,
    "EventItemTitle": "Roll Call",
    "EventItemTally": null,
    "EventItemAccelaRecordId": null,
    "EventItemConsent": 0,
    "EventItemMoverId": null,
    "EventItemMover": null,
    "EventItemSeconderId": null,
    "EventItemSeconder": null,
    "EventItemMatterId": null,
    "EventItemMatterGuid": null,
    "EventItemMatterFile": null,
    "EventItemMatterName": null,
    "EventItemMatterType": null,
    "EventItemMatterStatus": null,
    "EventItemMatterAttachments": []
},{
    "EventItemId": 287665,
    "EventItemGuid": "BAAF912C-15FF-4B8F-818D-BFDA54FC5559",
    "EventItemLastModifiedUtc": "2015-08-25T15:58:59.527",
    "EventItemRowVersion": "AAAAAB9qkWI=",
    "EventItemEventId": 13196,
    "EventItemAgendaSequence": null,
    "EventItemMinutesSequence": 4,
    "EventItemAgendaNumber": null,
    "EventItemVideo": null,
    "EventItemVideoIndex": null,
    "EventItemVersion": "*",
    "EventItemAgendaNote": null,
    "EventItemMinutesNote": null,
    "EventItemActionId": 5031,
    "EventItemActionName": "Filed, by Committee",
    "EventItemActionText": "This Oversight was Filed, by Committee",
    "EventItemPassedFlag": null,
    "EventItemPassedFlagName": null,
    "EventItemRollCallFlag": 0,
    "EventItemFlagExtra": null,
    "EventItemTitle": "Oversight – Is the City doing enough to increase access to capital and credit readiness for small businesses?",
    "EventItemTally": null,
    "EventItemAccelaRecordId": null,
    "EventItemConsent": 0,
    "EventItemMoverId": null,
    "EventItemMover": null,
    "EventItemSeconderId": null,
    "EventItemSeconder": null,
    "EventItemMatterId": 52441,
    "EventItemMatterGuid": "AD00C423-2879-45A4-A8CD-07741F4139E5",
    "EventItemMatterFile": "T2014-0907",
    "EventItemMatterName": "Oversight – Is the City doing enough to increase access to capital and credit readiness for small businesses?",
    "EventItemMatterType": "Oversight",
    "EventItemMatterStatus": "Filed",
    "EventItemMatterAttachments": []
},{
    "EventItemId": 287736,
    "EventItemGuid": "E46A4B03-8189-4965-A14E-03F4CFABE1E5",
    "EventItemLastModifiedUtc": "2015-08-25T15:58:59.527",
    "EventItemRowVersion": "AAAAAB9qkU4=",
    "EventItemEventId": 13196,
    "EventItemAgendaSequence": null,
    "EventItemMinutesSequence": 2,
    "EventItemAgendaNumber": null,
    "EventItemVideo": null,
    "EventItemVideoIndex": null,
    "EventItemVersion": null,
    "EventItemAgendaNote": null,
    "EventItemMinutesNote": null,
    "EventItemActionId": null,
    "EventItemActionName": null,
    "EventItemActionText": null,
    "EventItemPassedFlag": null,
    "EventItemPassedFlagName": null,
    "EventItemRollCallFlag": 0,
    "EventItemFlagExtra": null,
    "EventItemTitle": null,
    "EventItemTally": null,
    "EventItemAccelaRecordId": null,
    "EventItemConsent": 0,
    "EventItemMoverId": null,
    "EventItemMover": null,
    "EventItemSeconderId": null,
    "EventItemSeconder": null,
    "EventItemMatterId": null,
    "EventItemMatterGuid": null,
    "EventItemMatterFile": null,
    "EventItemMatterName": null,
    "EventItemMatterType": null,
    "EventItemMatterStatus": null,
    "EventItemMatterAttachments": []
},